contextmcp.py
context_control/__init__.py
context_control/api.py
context_control/cli.py
context_control/client.py
context_control/mcp_server.py
context_control/models.py
context_control/storage.py
context_control-0.0.1.dist-info/METADATA
context_control-0.0.1.dist-info/WHEEL
context_control-0.0.1.dist-info/entry_points.txt
context_control-0.0.1.dist-info/top_level.txt
context_control-0.0.1.dist-info/RECORD
