Metadata-Version: 2.4
Name: context-control
Version: 0.0.1
Summary: FastAPI service and toolkit for managing AI agent contexts, prompts, and memories.
Author: Context Control Maintainers
License: MIT
Project-URL: Homepage, https://context-control.com
Project-URL: Repository, https://github.com/example/context-control
Requires-Python: >=3.9
Requires-Dist: fastapi>=0.110
Requires-Dist: uvicorn>=0.22
Requires-Dist: sqlalchemy>=2.0
Requires-Dist: pydantic>=2.0
Requires-Dist: requests>=2.31
